mctoast/__init__.py
mctoast/__main__.py
mctoast/assets/mctoast/fonts/unifont.otf
mctoast/assets/mctoast/textures/advancement.png
mctoast/assets/mctoast/textures/recipe.png
mctoast/assets/mctoast/textures/system.png
mctoast-1.21.dist-info/LICENSE.md
mctoast-1.21.dist-info/LICENSE.让我们说中文.md
mctoast-1.21.dist-info/METADATA
mctoast-1.21.dist-info/WHEEL
mctoast-1.21.dist-info/entry_points.txt
mctoast-1.21.dist-info/top_level.txt
mctoast-1.21.dist-info/RECORD
