Metadata-Version: 2.2
Name: mctoast
Version: 1.21
Summary: 把Minecraft的Toast带到现实里！
Home-page: https://github.com/SystemFileB/mctoast
Author: SystemFileB
License: GNU Lesser General Public License v3 (LGPLv3)
Classifier: Programming Language :: Python :: 3
Classifier: License :: OSI Approved :: GNU Lesser General Public License v3 (LGPLv3)
Classifier: Operating System :: OS Independent
License-File: LICENSE.md
License-File: LICENSE.让我们说中文.md
Requires-Dist: pillow
Dynamic: author
Dynamic: classifier
Dynamic: description
Dynamic: description-content-type
Dynamic: home-page
Dynamic: license
Dynamic: requires-dist
Dynamic: summary
